tnz/__init__.py
tnz/_termlib.py
tnz/_util.py
tnz/_version.py
tnz/ati.py
tnz/cp310.py
tnz/ditto.py
tnz/logging.json
tnz/py3270.py
tnz/rexx.py
tnz/tnz.py
tnz/zti.py
tnz-0.6.3.dist-info/licenses/LICENSE
tnz-0.6.3.dist-info/METADATA
tnz-0.6.3.dist-info/WHEEL
tnz-0.6.3.dist-info/entry_points.txt
tnz-0.6.3.dist-info/top_level.txt
tnz-0.6.3.dist-info/RECORD
