Metadata-Version: 2.4
Name: tnz
Version: 0.6.3
Summary: Telnet-3270 to Z tool and library
Author: Neil Johnson
Author-email: najohnsn@us.ibm.com
License: Apache-2.0
Project-URL: documentation, https://ibm.github.io/tnz
Project-URL: homepage, https://github.com/IBM/tnz
Project-URL: issues, https://github.com/IBM/tnz/issues
Project-URL: releasenotes, https://github.com/IBM/tnz/releases/latest
Project-URL: source, https://github.com/IBM/tnz
Requires-Python: >=3.9
License-File: LICENSE
Provides-Extra: full
Requires-Dist: ebcdic; extra == "full"
Dynamic: license-file
